{
    "parameters": {
      "aftag": "gnomADg_AF",
      "afthr": 0.01
    },
    "workflow_uuid": "8e075e1f-95ae-41f3-8f25-527d80af0787",
    "input_files" : [
       {
           "workflow_argument_name": "input_vcf",
           "uuid": "",
           "unzip": "gz"
       },
       {
           "workflow_argument_name": "genes",
           "uuid": "84f2bb24-edd7-459b-ab89-0a21866d7826"
       }
    ],
    "config": {
      "instance_type": "t3.medium",
      "ebs_size": "6x",
      "EBS_optimized": true,
      "spot_instance": true,
      "log_bucket": "tibanna-output",
      "run_name": "run_workflow_granite-filtering-check",
      "behavior_on_capacity_limit": "wait_and_retry"
    },
    "_tibanna": {
      "run_type": "workflow_granite-filtering-check",
      "env": "fourfront-cgap"
    },
    "app_name": "workflow_granite-filtering-check"
}
